rlms/__init__.py
rlms-0.0.1a1.dist-info/METADATA
rlms-0.0.1a1.dist-info/WHEEL
rlms-0.0.1a1.dist-info/top_level.txt
rlms-0.0.1a1.dist-info/RECORD
