Metadata-Version: 2.4
Name: rlms
Version: 0.0.1a1
Summary: Python package.
Author: 
Requires-Python: >=3.8
